romanRekhta/__init__.py
romanRekhta/preprocessing.py
romanRekhta/stopwords.py
romanRekhta/tokenizer.py
romanrekhta-0.1.0.dist-info/METADATA
romanrekhta-0.1.0.dist-info/WHEEL
romanrekhta-0.1.0.dist-info/top_level.txt
romanrekhta-0.1.0.dist-info/RECORD
