Metadata-Version: 2.4
Name: romanRekhta
Version: 0.1.0
Summary: An NLP library for Roman Urdu text preprocessing, tokenization, and stopword handling.
Home-page: https://github.com/is-ammar/romanRekhta
Author: Muhammad Ammar
Author-email: ammarshafique677@gmail.com
License: MIT
Project-URL: Source, https://github.com/is-ammar/romanRekhta
Project-URL: Tracker, https://github.com/is-ammar/romanRekhta/issues
Keywords: roman urdu nlp stopwords tokenization emoji preprocessing
Classifier: Development Status :: 3 - Alpha
Classifier: Intended Audience :: Developers
Classifier: Intended Audience :: Science/Research
Classifier: Topic :: Text Processing :: Linguistic
Classifier: License :: OSI Approved :: MIT License
Classifier: Programming Language :: Python :: 3.7
Classifier: Programming Language :: Python :: 3.8
Classifier: Programming Language :: Python :: 3.9
Requires-Python: >=3.7
Requires-Dist: emoji>=2.0.0
Dynamic: author
Dynamic: author-email
Dynamic: classifier
Dynamic: description
Dynamic: description-content-type
Dynamic: home-page
Dynamic: keywords
Dynamic: license
Dynamic: project-url
Dynamic: requires-dist
Dynamic: requires-python
Dynamic: summary
